{
    "Corp_Frigider_12_usi_Gola": {
        "metadata": {
            "constructie": "Laterale pe baza",
            "versiune": "3.0_le_li"
        },
        "piese": [
            {
                "nume": "Baza corp frigider 2 usi+Gola",
                "L": "L",
                "l": "A",
                "cantitate": 1,
                "fibra": 0,
                "ABS": {
                    "L1": 0.4,
                    "L2": 0,
                    "l1": 0.4,
                    "l2": 0.4
                },
                "material": "PAL_ALB"
            },
            {
                "nume": "Laterala corp PAL",
                "L": "H - 18",
                "l": "A",
                "cantitate": 1,
                "fibra": 0,
                "ABS": {
                    "L1": 0.4,
                    "L2": 0,
                    "l1": 0,
                    "l2": 0
                },
                "material": "PAL_ALB"
            },
            {
                "nume": "Lateral corp Vizibila",
                "L": "H - 18",
                "l": "A",
                "cantitate": 1,
                "fibra": 0,
                "ABS": {
                    "L1": 0.4,
                    "L2": 0,
                    "l1": 0,
                    "l2": 0
                },
                "material": "Vizibil"
            },
            {
                "nume": "Capac corp",
                "L": "L-36",
                "l": "A-50",
                "cantitate": 1,
                "fibra": 0,
                "ABS": {
                    "L1": 0.4,
                    "L2": 0,
                    "l1": 0.4,
                    "l2": 0.4
                },
                "material": "PAL_ALB"
            },
            {
                "nume": "Polita",
                "L": "L - 36",
                "l": "A - 50",
                "cantitate": 1,
                "fibra": 0,
                "ABS": {
                    "L1": 0.4,
                    "L2": 0,
                    "l1": 0,
                    "l2": 0
                },
                "material": "PAL_ALB"
            },
            {
                "nume": "Placa inchidere",
                "L": "H + 100",
                "l": "100",
                "cantitate": 1,
                "fibra": 0,
                "ABS": {
                    "L1": 0.4,
                    "L2": 0,
                    "l1": 0.4,
                    "l2": 0.4
                },
                "material": "Vizibil"
            },
            {
                "nume": "Usa jos",
                "L": "HA - 30 ",
                "l": "L - (2 * le)",
                "cantitate": 1,
                "fibra": 0,
                "material": "FRONT",
                "ABS": {
                    "L1": "scadere_cant",
                    "L2": "scadere_cant",
                    "l1": "scadere_cant",
                    "l2": "scadere_cant"
                }
            },
            {
                "nume": "Usa sus",
                "L": "H - HA-(2 * le) ",
                "l": "L - (2 * le)",
                "cantitate": 1,
                "fibra": 0,
                "material": "FRONT",
                "ABS": {
                    "L1": "scadere_cant",
                    "L2": "scadere_cant",
                    "l1": "scadere_cant",
                    "l2": "scadere_cant"
                }
            }
        ]
    }
}